gopm/__init__.py
gopm/__main__.py
gopm/git.py
gopm/main.py
gopm/project.py
gopm/py.typed
gopm/search/github.py
gopm/search/search_provider.py
gopm-3.1.1.dist-info/METADATA
gopm-3.1.1.dist-info/WHEEL
gopm-3.1.1.dist-info/entry_points.txt
gopm-3.1.1.dist-info/licenses/LICENSE
gopm-3.1.1.dist-info/RECORD
