Metadata-Version: 2.1
Name: gopm
Version: 3.1.1
Summary: A package manager for the Godot Engine
Project-URL: Homepage, https://github.com/jummit/godot-package-manager
Project-URL: Bug Tracker, https://github.com/jummit/godot-package-manager/issues
Author-email: Jummit <jummit@web.com>
License-File: LICENSE
Classifier: Development Status :: 3 - Alpha
Classifier: Intended Audience :: Developers
Classifier: License :: OSI Approved :: MIT License
Classifier: Natural Language :: English
Classifier: Operating System :: OS Independent
Classifier: Programming Language :: Python :: 3
Classifier: Topic :: Software Development :: Build Tools
Classifier: Topic :: System :: Installation/Setup
Classifier: Typing :: Typed
Requires-Python: >=3.7
Requires-Dist: requests
Requires-Dist: send2trash
